amazon/__init__.py
amazon/amazon.py
amazon/currencies.py
amazon/languages.py
ebay/__init__.py
ebay/domains.py
ebay/ebay.py
google_shopping/__init__.py
google_shopping/countries.py
google_shopping/domains.py
google_shopping/google_shopping.py
google_shopping/languages.py
home_depot/__init__.py
home_depot/home_depot.py
walmart/__init__.py
walmart/stores.py
walmart/walmart.py
ecommerce_scraper_py-0.1.1.dist-info/LICENSE
ecommerce_scraper_py-0.1.1.dist-info/METADATA
ecommerce_scraper_py-0.1.1.dist-info/WHEEL
ecommerce_scraper_py-0.1.1.dist-info/top_level.txt
ecommerce_scraper_py-0.1.1.dist-info/RECORD
