Metadata-Version: 2.1
Name: ecommerce-scraper-py
Version: 0.1.1
Summary: Scrape ecommerce websites such as Amazon, eBay, Walmart, Home Depot, Google Shopping from a single module in Python🐍
Home-page: https://github.com/dimitryzub/ecommerce-scraper-py
Author: Artur Chukhrai
Author-email: chukhraiartur@gmail.com
Maintainer: Artur Chukhrai, Dmitiry Zub
Maintainer-email: chukhraiartur@gmail.com, dimitryzub@gmail.com
License: MIT
Project-URL: Documentation, https://github.com/dimitryzub/ecommerce-scraper-py
Project-URL: Source, https://github.com/dimitryzub/ecommerce-scraper-py
Project-URL: Tracker, https://github.com/dimitryzub/ecommerce-scraper-py/issues
Keywords: amazon,ebay,home depot,walmart,google shopping,serpapi,scraper,python,ecommerce,e-commerce,web scraping,python web scraping,google-search-results
Classifier: Development Status :: 3 - Alpha
Classifier: Intended Audience :: Developers
Classifier: Operating System :: Microsoft :: Windows
Classifier: Operating System :: MacOS
Classifier: Operating System :: POSIX :: Linux
Classifier: Topic :: Internet
Classifier: Natural Language :: English
Classifier: Topic :: Utilities
Classifier: Programming Language :: Python :: 3.8
Classifier: Programming Language :: Python :: 3.9
Classifier: Programming Language :: Python :: 3.10
Classifier: License :: OSI Approved :: MIT License
Requires-Python: >=3.8
License-File: LICENSE
Requires-Dist: google-search-results (>=2.4)
Requires-Dist: selenium (>=4.3)
Requires-Dist: selectolax (>=0.3)
Requires-Dist: webdriver-manager (>=3.8)
Requires-Dist: selenium-stealth (>=1.0)
